hiad/__init__.py
hiad/datasets/__init__.py
hiad/datasets/patch_dataset.py
hiad/datasets/syn_dataset.py
hiad/detectors/__init__.py
hiad/detectors/base.py
hiad/detectors/hr_destseg.py
hiad/detectors/hr_dinomaly.py
hiad/detectors/hr_fastflow.py
hiad/detectors/hr_inpformer.py
hiad/detectors/hr_padim.py
hiad/detectors/hr_patchcore.py
hiad/detectors/hr_rdpp.py
hiad/detectors/hr_realnet.py
hiad/detectors/hr_vitad.py
hiad/detectors/destseg/__init__.py
hiad/detectors/destseg/model/__init__.py
hiad/detectors/destseg/model/destseg.py
hiad/detectors/destseg/model/losses.py
hiad/detectors/destseg/model/metrics.py
hiad/detectors/destseg/model/model_utils.py
hiad/detectors/dinomaly/__init__.py
hiad/detectors/dinomaly/utils.py
hiad/detectors/dinomaly/dinov1/__init__.py
hiad/detectors/dinomaly/dinov1/utils.py
hiad/detectors/dinomaly/dinov1/vision_transformer.py
hiad/detectors/dinomaly/dinov2/__init__.py
hiad/detectors/dinomaly/dinov2/configs/__init__.py
hiad/detectors/dinomaly/dinov2/data/__init__.py
hiad/detectors/dinomaly/dinov2/data/adapters.py
hiad/detectors/dinomaly/dinov2/data/augmentations.py
hiad/detectors/dinomaly/dinov2/data/collate.py
hiad/detectors/dinomaly/dinov2/data/loaders.py
hiad/detectors/dinomaly/dinov2/data/masking.py
hiad/detectors/dinomaly/dinov2/data/samplers.py
hiad/detectors/dinomaly/dinov2/data/transforms.py
hiad/detectors/dinomaly/dinov2/data/datasets/__init__.py
hiad/detectors/dinomaly/dinov2/data/datasets/decoders.py
hiad/detectors/dinomaly/dinov2/data/datasets/extended.py
hiad/detectors/dinomaly/dinov2/data/datasets/image_net.py
hiad/detectors/dinomaly/dinov2/data/datasets/image_net_22k.py
hiad/detectors/dinomaly/dinov2/distributed/__init__.py
hiad/detectors/dinomaly/dinov2/eval/__init__.py
hiad/detectors/dinomaly/dinov2/eval/knn.py
hiad/detectors/dinomaly/dinov2/eval/linear.py
hiad/detectors/dinomaly/dinov2/eval/log_regression.py
hiad/detectors/dinomaly/dinov2/eval/metrics.py
hiad/detectors/dinomaly/dinov2/eval/setup.py
hiad-0.2.1.dist-info/LICENSE
hiad-0.2.1.dist-info/METADATA
hiad-0.2.1.dist-info/WHEEL
hiad-0.2.1.dist-info/top_level.txt
hiad-0.2.1.dist-info/RECORD
